nonebot_plugin_htmlrender/__init__.py
nonebot_plugin_htmlrender/browser.py
nonebot_plugin_htmlrender/config.py
nonebot_plugin_htmlrender/data_source.py
liteyukibot_plugin_htmlrender-0.1.0.dist-info/LICENSE.md
liteyukibot_plugin_htmlrender-0.1.0.dist-info/METADATA
liteyukibot_plugin_htmlrender-0.1.0.dist-info/WHEEL
liteyukibot_plugin_htmlrender-0.1.0.dist-info/top_level.txt
liteyukibot_plugin_htmlrender-0.1.0.dist-info/RECORD
