Metadata-Version: 2.1
Name: liteyukibot-plugin-htmlrender
Version: 0.1.0
Summary: 提供跨平台的多用途页面渲染功能，是nontbot-plugin-htmlrender的高级替代
Author-email: Eilles <EillesWan@outlook.com>
License: 汉钰律许可协议 第一版
Requires-Python: >=3.10
License-File: LICENSE.md
Requires-Dist: liteyukibot >=6.3.9
